katt.py
katt-0.1.dist-info/LICENSE
katt-0.1.dist-info/WHEEL
katt-0.1.dist-info/METADATA
katt-0.1.dist-info/RECORD
