Metadata-Version: 2.1
Name: katt
Version: 0.1
Summary: defn: define infrastructure
Author-email: defn Nghiem <iam@defn.sh>
Classifier: License :: OSI Approved :: Apache Software License
Project-URL: Home, https://defn.sh/katt
